{
	"name": "Fullload",
	"properties": {
		"activities": [
			{
				"name": "Fulload_pipeline_lookup",
				"type": "Lookup",
				"dependsOn": [],
				"policy": {
					"timeout": "0.12:00:00",
					"retry": 0,
					"retryIntervalInSeconds": 30,
					"secureOutput": false,
					"secureInput": false
				},
				"userProperties": [],
				"typeProperties": {
					"source": {
						"type": "AzureSqlSource",
						"sqlReaderQuery": "select * from dbo.Pipeline_INC_FULLtblconfig where is_active=1",
						"queryTimeout": "02:00:00",
						"partitionOption": "None"
					},
					"dataset": {
						"referenceName": "AzureSqlTable1",
						"type": "DatasetReference"
					},
					"firstRowOnly": false
				}
			},
			{
				"name": "ForEach1",
				"type": "ForEach",
				"dependsOn": [
					{
						"activity": "Fulload_pipeline_lookup",
						"dependencyConditions": [
							"Succeeded"
						]
					}
				],
				"userProperties": [],
				"typeProperties": {
					"items": {
						"value": "@activity('Fulload_pipeline_lookup').output.value",
						"type": "Expression"
					},
					"isSequential": true,
					"activities": [
						{
							"name": "Copy data1",
							"type": "Copy",
							"dependsOn": [
								{
									"activity": "Lookup1",
									"dependencyConditions": [
										"Succeeded"
									]
								}
							],
							"policy": {
								"timeout": "0.12:00:00",
								"retry": 0,
								"retryIntervalInSeconds": 30,
								"secureOutput": false,
								"secureInput": false
							},
							"userProperties": [],
							"typeProperties": {
								"source": {
									"type": "AzureSqlSource",
									"sqlReaderQuery": {
										"value": "select * from @{item().srcschema}.@{item().srctable};",
										"type": "Expression"
									},
									"queryTimeout": "02:00:00",
									"partitionOption": "None"
								},
								"sink": {
									"type": "DelimitedTextSink",
									"storeSettings": {
										"type": "AzureBlobFSWriteSettings"
									},
									"formatSettings": {
										"type": "DelimitedTextWriteSettings",
										"quoteAllText": true,
										"fileExtension": ".txt"
									}
								},
								"enableStaging": false,
								"translator": {
									"type": "TabularTranslator",
									"typeConversion": true,
									"typeConversionSettings": {
										"allowDataTruncation": true,
										"treatBooleanAsNumber": false
									}
								}
							},
							"inputs": [
								{
									"referenceName": "AzureSqlTable1",
									"type": "DatasetReference"
								}
							],
							"outputs": [
								{
									"referenceName": "Incfile_csv",
									"type": "DatasetReference",
									"parameters": {
										"sink_container": "@item().sinkcontainer",
										"sink_folder": "@item().sinkfolder_Full",
										"sink_table": "@concat(formatDateTime(utcNow(),'yyyy/MM/dd'),'/',item().srctable)"
									}
								}
							]
						},
						{
							"name": "Lookup1",
							"type": "Lookup",
							"dependsOn": [],
							"policy": {
								"timeout": "0.12:00:00",
								"retry": 0,
								"retryIntervalInSeconds": 30,
								"secureOutput": false,
								"secureInput": false
							},
							"userProperties": [],
							"typeProperties": {
								"source": {
									"type": "AzureSqlSource",
									"sqlReaderQuery": {
										"value": "select max(@{item().deltacol}) as maxvalue from @{item().srcschema}.@{item().srctable}",
										"type": "Expression"
									},
									"queryTimeout": "02:00:00",
									"partitionOption": "None"
								},
								"dataset": {
									"referenceName": "AzureSqlTable1",
									"type": "DatasetReference"
								}
							}
						},
						{
							"name": "Stored procedure1",
							"type": "SqlServerStoredProcedure",
							"dependsOn": [
								{
									"activity": "Copy data1",
									"dependencyConditions": [
										"Succeeded"
									]
								}
							],
							"policy": {
								"timeout": "0.12:00:00",
								"retry": 0,
								"retryIntervalInSeconds": 30,
								"secureOutput": false,
								"secureInput": false
							},
							"userProperties": [],
							"typeProperties": {
								"storedProcedureName": "[dbo].[tblconfig_INC_FULL]",
								"storedProcedureParameters": {
									"id": {
										"value": {
											"value": "@item().id",
											"type": "Expression"
										},
										"type": "Int32"
									},
									"lpv_param": {
										"value": {
											"value": "@activity('Lookup1').output.firstRow.maxvalue",
											"type": "Expression"
										},
										"type": "String"
									}
								}
							},
							"linkedServiceName": {
								"referenceName": "SQLdatabase_Keerthi",
								"type": "LinkedServiceReference"
							}
						},
						{
							"name": "Notebook1",
							"type": "DatabricksNotebook",
							"dependsOn": [
								{
									"activity": "Stored procedure1",
									"dependencyConditions": [
										"Succeeded"
									]
								}
							],
							"policy": {
								"timeout": "0.12:00:00",
								"retry": 0,
								"retryIntervalInSeconds": 30,
								"secureOutput": false,
								"secureInput": false
							},
							"userProperties": [],
							"linkedServiceName": {
								"referenceName": "AzureDatabricks1",
								"type": "LinkedServiceReference"
							}
						}
					]
				}
			}
		],
		"variables": {
			"test": {
				"type": "String"
			}
		},
		"annotations": []
	}
}